nazo_ip2asn/__init__.py
nazo_ip2asn/ip2asn.cpp
nazo_ip2asn/ip2asn.cpython-310-darwin.so
nazo_ip2asn/ip2asn.pyi
nazo_ip2asn/ip2asn.pyx
nazo_ip2asn/ipasn.hpp
nazo_ip2asn-0.0.4.dist-info/LICENSE
nazo_ip2asn-0.0.4.dist-info/METADATA
nazo_ip2asn-0.0.4.dist-info/WHEEL
nazo_ip2asn-0.0.4.dist-info/top_level.txt
nazo_ip2asn-0.0.4.dist-info/RECORD
